ckanext/__init__.py
ckanext/versioned_datastore/__init__.py
ckanext/versioned_datastore/cli.py
ckanext/versioned_datastore/helpers.py
ckanext/versioned_datastore/interfaces.py
ckanext/versioned_datastore/plugin.py
ckanext/versioned_datastore/lib/__init__.py
ckanext/versioned_datastore/lib/common.py
ckanext/versioned_datastore/lib/tasks.py
ckanext/versioned_datastore/lib/utils.py
ckanext/versioned_datastore/lib/downloads/__init__.py
ckanext/versioned_datastore/lib/downloads/download.py
ckanext/versioned_datastore/lib/downloads/loaders.py
ckanext/versioned_datastore/lib/downloads/utils.py
ckanext/versioned_datastore/lib/downloads/derivatives/__init__.py
ckanext/versioned_datastore/lib/downloads/derivatives/base.py
ckanext/versioned_datastore/lib/downloads/derivatives/csv.py
ckanext/versioned_datastore/lib/downloads/derivatives/json.py
ckanext/versioned_datastore/lib/downloads/derivatives/dwc/__init__.py
ckanext/versioned_datastore/lib/downloads/derivatives/dwc/generator.py
ckanext/versioned_datastore/lib/downloads/derivatives/dwc/schema.py
ckanext/versioned_datastore/lib/downloads/derivatives/dwc/schema_parts.py
ckanext/versioned_datastore/lib/downloads/derivatives/dwc/urls.py
ckanext/versioned_datastore/lib/downloads/derivatives/dwc/utils.py
ckanext/versioned_datastore/lib/downloads/notifiers/__init__.py
ckanext/versioned_datastore/lib/downloads/notifiers/base.py
ckanext/versioned_datastore/lib/downloads/notifiers/email.py
ckanext/versioned_datastore/lib/downloads/notifiers/null.py
ckanext/versioned_datastore/lib/downloads/notifiers/webhook.py
ckanext/versioned_datastore/lib/downloads/servers/__init__.py
ckanext/versioned_datastore/lib/downloads/servers/base.py
ckanext/versioned_datastore/lib/downloads/servers/direct.py
ckanext/versioned_datastore/lib/downloads/transforms/__init__.py
ckanext/versioned_datastore/lib/downloads/transforms/base.py
ckanext/versioned_datastore/lib/downloads/transforms/id_as_url.py
ckanext/versioned_datastore/lib/importing/__init__.py
ckanext_versioned_datastore-6.5.2.dist-info/licenses/LICENSE
ckanext_versioned_datastore-6.5.2.dist-info/METADATA
ckanext_versioned_datastore-6.5.2.dist-info/WHEEL
ckanext_versioned_datastore-6.5.2.dist-info/entry_points.txt
ckanext_versioned_datastore-6.5.2.dist-info/top_level.txt
ckanext_versioned_datastore-6.5.2.dist-info/RECORD
