Metadata-Version: 2.4
Name: ckanext-versioned-datastore
Version: 6.5.2
Summary: A CKAN extension providing a versioned datastore using MongoDB and Elasticsearch
Author-email: Natural History Museum <data@nhm.ac.uk>
License: GPL-3.0-or-later
Project-URL: repository, https://github.com/NaturalHistoryMuseum/ckanext-versioned-datastore
Project-URL: changelog, https://github.com/NaturalHistoryMuseum/ckanext-versioned-datastore/blob/main/CHANGELOG.md
Keywords: CKAN,data,versioned_datastore
Classifier: Development Status :: 5 - Production/Stable
Classifier: License :: OSI Approved :: GNU General Public License v3 (GPLv3)
Classifier: Programming Language :: Python
Classifier: Programming Language :: Python :: 3 :: Only
Classifier: Programming Language :: Python :: 3.6
Classifier: Programming Language :: Python :: 3.7
Classifier: Programming Language :: Python :: 3.8
Requires-Python: >=3.6
License-File: LICENSE
Requires-Dist: splitgill>=3.2.2
Requires-Dist: importlib-resources
Requires-Dist: backports.csv==1.0.6
Requires-Dist: cchardet==2.1.4
Requires-Dist: elasticsearch>=8.10.1
Requires-Dist: elasticsearch-dsl~=8.13.1
Requires-Dist: jsonschema==3.0.0
Requires-Dist: openpyxl==2.5.8
Requires-Dist: pandas==1.4.1
Requires-Dist: requests
Requires-Dist: six>=1.11.0
Requires-Dist: xlrd==1.1.0
Requires-Dist: fastavro==1.7.0
Requires-Dist: cachetools>=4.2.4
Requires-Dist: ckantools>=0.4.2
Provides-Extra: test
Requires-Dist: mock; extra == "test"
Requires-Dist: pytest>=4.6.5; extra == "test"
Requires-Dist: pytest-cov>=2.7.1; extra == "test"
Requires-Dist: coveralls; extra == "test"
Provides-Extra: doi
Requires-Dist: ckanext-query-dois~=5.0.0; extra == "doi"
Provides-Extra: attribution
Requires-Dist: ckanext-attribution~=1.2.13; extra == "attribution"
Dynamic: license-file
